django_mercury/__init__.py
django_mercury/config.py
django_mercury/export.py
django_mercury/monitor.py
django_mercury/n_plus_one.py
django_mercury/summary.py
django_mercury/management/__init__.py
django_mercury/management/commands/__init__.py
django_mercury/management/commands/mercury_test.py
django_mercury_performance-0.1.2.dist-info/licenses/LICENSE.txt
django_mercury_performance-0.1.2.dist-info/METADATA
django_mercury_performance-0.1.2.dist-info/WHEEL
django_mercury_performance-0.1.2.dist-info/entry_points.txt
django_mercury_performance-0.1.2.dist-info/top_level.txt
django_mercury_performance-0.1.2.dist-info/RECORD
