Metadata-Version: 2.4
Name: django-mercury-performance
Version: 0.1.2
Summary: A performance testing framework for Django that helps you understand and fix performance issues, not just detect them
Author-email: Django Mercury Team <mathewstormdev@gmail.com>
Maintainer-email: Mathew Storm <mathewstormdev@gmail.com>
License: GPL-3.0-or-later
Project-URL: Homepage, https://pypi.org/project/django-mercury-performance/
Project-URL: Documentation, https://github.com/80-20-Human-In-The-Loop/Django-Mercury-Performance-Testing/wiki
Project-URL: Repository, https://github.com/80-20-Human-In-The-Loop/Django-Mercury-Performance-Testing
Project-URL: Bug Tracker, https://github.com/80-20-Human-In-The-Loop/Django-Mercury-Performance-Testing/issues
Project-URL: Changelog, https://github.com/Django-Mercury/Performance-Testing/blob/main/CHANGELOG.md
Keywords: django,performance,testing,monitoring,optimization,n+1,queries,profiling,mercury,rest-framework,api,benchmarking
Classifier: Development Status :: 3 - Alpha
Classifier: Framework :: Django
Classifier: Framework :: Django :: 5.1
Classifier: Framework :: Django :: 5.2
Classifier: Intended Audience :: Developers
Classifier: Operating System :: OS Independent
Classifier: Programming Language :: Python
Classifier: Programming Language :: Python :: 3
Classifier: Programming Language :: Python :: 3.10
Classifier: Programming Language :: Python :: 3.11
Classifier: Programming Language :: Python :: 3.12
Classifier: Topic :: Software Development :: Libraries :: Python Modules
Classifier: Topic :: Software Development :: Testing
Classifier: Topic :: Software Development :: Testing :: Unit
Classifier: Topic :: Software Development :: Quality Assurance
Requires-Python: >=3.10
License-File: LICENSE.txt
Requires-Dist: Django<6.0,>=3.2
Requires-Dist: djangorestframework>=3.12.0
Requires-Dist: psutil>=5.8.0
Requires-Dist: memory-profiler>=0.60.0
Requires-Dist: colorlog>=6.6.0
Requires-Dist: jsonschema>=4.0.0
Requires-Dist: toml>=0.10.2
Requires-Dist: rich>=12.0.0
Provides-Extra: rich
Requires-Dist: rich>=12.0.0; extra == "rich"
Provides-Extra: dev
Requires-Dist: pytest>=7.0.0; extra == "dev"
Requires-Dist: pytest-cov>=3.0.0; extra == "dev"
Requires-Dist: black>=22.0.0; extra == "dev"
Requires-Dist: isort>=5.10.0; extra == "dev"
Requires-Dist: mypy>=1.0.0; extra == "dev"
Requires-Dist: django-stubs[compatible-mypy]>=4.2.0; extra == "dev"
Requires-Dist: djangorestframework-stubs>=3.14.0; extra == "dev"
Requires-Dist: types-psutil>=5.9.0; extra == "dev"
Requires-Dist: rich>=12.0.0; extra == "dev"
Requires-Dist: flake8>=4.0.0; extra == "dev"
Requires-Dist: ruff>=0.1.0; extra == "dev"
Requires-Dist: coverage>=6.0.0; extra == "dev"
Requires-Dist: twine>=5.0.0; extra == "dev"
Requires-Dist: setuptools>=70.0; extra == "dev"
Requires-Dist: build>=1.0.0; extra == "dev"
Provides-Extra: docs
Requires-Dist: sphinx>=4.5.0; extra == "docs"
Requires-Dist: sphinx-rtd-theme>=1.0.0; extra == "docs"
Provides-Extra: debug
Requires-Dist: django-debug-toolbar>=3.2.0; extra == "debug"
Requires-Dist: django-silk>=4.3.0; extra == "debug"
Dynamic: license-file
